<?xml version="1.0" encoding="utf-8"?>
<StructureDefinition xmlns="http://hl7.org/fhir">
  <url value="http://nictiz.nl/fhir/StructureDefinition/bc-MaternalObservation" />
  <name value="bc-MaternalObservation" />
  <status value="draft" />
  <description value="An Observation profile describing patient-related Observations, which are not captured in other existing profiles, as defined by BabyConnect. Patient-related Observations are about the (pregnant) woman, which is the subject of the Observation." />
  <fhirVersion value="3.0.2" />
  <mapping>
    <identity value="hcim-basicelements-v1.0-2017EN" />
    <uri value="https://zibs.nl/wiki/BasicElements-v1.0(2017EN)" />
    <name value="HCIM BasicElements-v1.0(2017EN)" />
  </mapping>
  <mapping>
    <identity value="gebz-peri-v2.3" />
    <uri value="https://decor.nictiz.nl/art-decor/decor-datasets--peri20-?id=2.16.840.1.113883.2.4.3.11.60.90.77.1.6&amp;effectiveDate=2016-09-08T00%3A00%3A00&amp;conceptId=2.16.840.1.113883.2.4.3.11.60.90.77.2.6.40050&amp;conceptEffectiveDate=2016-09-08T00%3A00%3A00" />
    <name value="Geboortezorg Perinatologie 2.3" />
  </mapping>
  <kind value="resource" />
  <abstract value="false" />
  <type value="Observation" />
  <baseDefinition value="http://fhir.nl/fhir/StructureDefinition/nl-core-observation" />
  <derivation value="constraint" />
  <differential>
    <element id="Observation.subject">
      <path value="Observation.subject" />
      <type>
        <code value="Reference" />
        <targetProfile value="http://nictiz.nl/fhir/StructureDefinition/StructureDefinition/bc-Woman" />
      </type>
      <mapping>
        <identity value="gebz-peri-v2.3" />
        <map value="peri23-dataelement-2" />
        <comment value="Vrouw" />
      </mapping>
    </element>
    <element id="Observation.context">
      <path value="Observation.context" />
      <type>
        <code value="Reference" />
        <targetProfile value="http://nictiz.nl/fhir/StructureDefinition/bc-MaternalRecord" />
      </type>
      <type>
        <code value="Reference" />
        <targetProfile value="http://nictiz.nl/fhir/StructureDefinition/bc-Encounter" />
      </type>
      <type>
        <code value="Reference" />
        <targetProfile value="http://nictiz.nl/fhir/StructureDefinition/bc-ChildBirthAssistance" />
      </type>
      <mapping>
        <identity value="gebz-peri-v2.3" />
        <map value="peri23-dataelement-4" />
        <comment value="Zorgverlening" />
      </mapping>
    </element>
    <element id="Observation.value[x]">
      <path value="Observation.value[x]" />
      <slicing>
        <discriminator>
          <type value="pattern" />
          <path value="$this" />
        </discriminator>
        <rules value="open" />
      </slicing>
    </element>
    <element id="Observation.value[x]:portio">
      <path value="Observation.value[x]" />
      <sliceName value="portio" />
      <type>
        <code value="CodeableConcept" />
      </type>
      <binding>
        <strength value="extensible" />
        <description value="CervixEffacement" />
        <valueSetUri value="http://decor.nictiz.nl/fhir/ValueSet/2.16.840.1.113883.2.4.11.158--20120317000000" />
      </binding>
      <mapping>
        <identity value="gebz-peri-v2.3" />
        <map value="peri23-dataelement-20612" />
        <comment value="Portio" />
      </mapping>
    </element>
    <element id="Observation.value[x]:portioPosition">
      <path value="Observation.value[x]" />
      <sliceName value="portioPosition" />
      <type>
        <code value="CodeableConcept" />
      </type>
      <binding>
        <strength value="extensible" />
        <description value="PositiePortio22" />
        <valueSetUri value="http://decor.nictiz.nl/fhir/ValueSet/2.16.840.1.113883.2.4.11.213--20160425122048" />
      </binding>
      <mapping>
        <identity value="gebz-peri-v2.3" />
        <map value="peri23-dataelement-20613" />
        <comment value="Ontsluiting" />
      </mapping>
    </element>
    <element id="Observation.value[x]:dilatation">
      <path value="Observation.value[x]" />
      <sliceName value="dilatation" />
      <type>
        <code value="CodeableConcept" />
      </type>
      <binding>
        <strength value="extensible" />
        <description value="CervicalDilatation" />
        <valueSetUri value="http://decor.nictiz.nl/fhir/ValueSet/2.16.840.1.113883.2.4.11.175--20130422173433" />
      </binding>
      <mapping>
        <identity value="gebz-peri-v2.3" />
        <map value="peri23-dataelement-20613" />
        <comment value="Ontsluiting" />
      </mapping>
    </element>
    <element id="Observation.value[x]:membranes">
      <path value="Observation.value[x]" />
      <sliceName value="membranes" />
      <type>
        <code value="CodeableConcept" />
      </type>
      <binding>
        <strength value="extensible" />
        <description value="Vliezen" />
        <valueSetUri value="http://decor.nictiz.nl/fhir/ValueSet/2.16.840.1.113883.2.4.11.173--20130320000000" />
      </binding>
      <mapping>
        <identity value="gebz-peri-v2.3" />
        <map value="peri23-dataelement-20614" />
        <comment value="Vliezen" />
      </mapping>
    </element>
    <element id="Observation.value[x]:hodgePlanes">
      <path value="Observation.value[x]" />
      <sliceName value="hodgePlanes" />
      <type>
        <code value="CodeableConcept" />
      </type>
      <binding>
        <strength value="extensible" />
        <description value="HodgePlanes" />
        <valueSetUri value="http://decor.nictiz.nl/fhir/ValueSet/2.16.840.1.113883.2.4.11.159--20120317000000" />
      </binding>
      <mapping>
        <identity value="gebz-peri-v2.3" />
        <map value="peri23-dataelement-20615" />
        <comment value="Indaling Hodge" />
      </mapping>
    </element>
    <element id="Observation.value[x]:fetusPresentation">
      <path value="Observation.value[x]" />
      <sliceName value="fetusPresentation" />
      <type>
        <code value="CodeableConcept" />
      </type>
      <binding>
        <strength value="extensible" />
        <description value="PresentationOfFetus" />
        <valueSetUri value="http://decor.nictiz.nl/fhir/ValueSet/2.16.840.1.113883.2.4.11.172--20130320000000" />
      </binding>
      <mapping>
        <identity value="gebz-peri-v2.3" />
        <map value="peri23-dataelement-80616" />
        <comment value="Aard van het voorliggend deel" />
      </mapping>
    </element>
    <element id="Observation.value[x]:position">
      <path value="Observation.value[x]" />
      <sliceName value="position" />
      <type>
        <code value="CodeableConcept" />
      </type>
      <binding>
        <strength value="extensible" />
        <description value="Stand" />
        <valueSetUri value="http://decor.nictiz.nl/fhir/ValueSet/2.16.840.1.113883.2.4.11.174--20151019205620" />
      </binding>
      <mapping>
        <identity value="gebz-peri-v2.3" />
        <map value="peri23-dataelement-80618" />
        <comment value="Stand" />
      </mapping>
    </element>
  </differential>
</StructureDefinition>